dieopt/__init__.py
dieopt/algo.py
dieopt/api.py
dieopt/draw_wafer.py
dieopt/models.py
dieopt-0.1.0.dist-info/licenses/LICENSE
dieopt-0.1.0.dist-info/METADATA
dieopt-0.1.0.dist-info/WHEEL
dieopt-0.1.0.dist-info/top_level.txt
dieopt-0.1.0.dist-info/RECORD
