Metadata-Version: 2.4
Name: dieopt
Version: 0.1.0
Summary: Die layout and optimisation tool
Author-email: Bjorn Schroder Nielsen <Bjorn@SchroderNielsen.com>
License-Expression: MPL-2.0
Project-URL: Homepage, https://github.com/BjornFS/dieopt
Project-URL: Issues, https://github.com/BjornFS/dieopt/issues
Requires-Python: >=3.8
License-File: LICENSE
Requires-Dist: numpy>=1.22
Requires-Dist: matplotlib
Dynamic: license-file
